squeylab/__init__.py
squeylab/send_to_squey.py
squeylab/cloud_providers/aws.py
send_to_squey-1.0.0.dist-info/METADATA
send_to_squey-1.0.0.dist-info/WHEEL
send_to_squey-1.0.0.dist-info/licenses/LICENSE
send_to_squey-1.0.0.dist-info/RECORD
