Metadata-Version: 2.3
Name: send-to-squey
Version: 1.0.0
Summary: Send columnar data structures from your code to a Squey cloud instance and visualize them.
Project-URL: Homepage, https://squeylab.com
Project-URL: Documentation, http://send-to-squey.doc.squeylab.com
Project-URL: Repository, https://gitlab.com/squeylab/send-to-squey
Project-URL: Issues, https://gitlab.com/squeylab/send-to-squey/issues
Project-URL: Changelog, https://send-to-squey.doc.squeylab.com/CHANGELOG
Author-email: Squeylab <contact@squeylab.com>
License-Expression: GPL-3.0-or-later
License-File: LICENSE
Classifier: License :: OSI Approved :: GNU General Public License v3 or later (GPLv3+)
Classifier: Operating System :: OS Independent
Classifier: Programming Language :: Python :: 3
Requires-Python: >=3.8
Requires-Dist: boto3
Requires-Dist: progress
Requires-Dist: pyarrow
